{
	"$schema": "http://schema.management.azure.com/schemas/2015-01-01/deploymentTemplate.json#",
	"contentVersion": "1.0.0.0",
	"parameters": {
		"factoryName": {
			"type": "string",
			"metadata": "Nombre de instancia de Data Factory",
			"defaultValue": "adf-ucb-sisinfo-13721058"
		}
	},
	"variables": {
		"factoryId": "[concat('Microsoft.DataFactory/factories/', parameters('factoryName'))]"
	},
	"resources": [
		{
			"name": "[concat(parameters('factoryName'), '/bronze_df_productos')]",
			"type": "Microsoft.DataFactory/factories/dataflows",
			"apiVersion": "2018-06-01",
			"properties": {
				"folder": {
					"name": "BRONZE"
				},
				"type": "MappingDataFlow",
				"typeProperties": {
					"sources": [
						{
							"dataset": {
								"referenceName": "productos_csv",
								"type": "DatasetReference"
							},
							"name": "source1"
						}
					],
					"sinks": [
						{
							"dataset": {
								"referenceName": "bronze_sql_productos",
								"type": "DatasetReference"
							},
							"name": "sink1"
						}
					],
					"transformations": [],
					"scriptLines": [
						"source(output(",
						"          prd_id as string,",
						"          prd_key as string,",
						"          prd_nm as string,",
						"          prd_cost as string,",
						"          prd_line as string",
						"     ),",
						"     allowSchemaDrift: true,",
						"     validateSchema: false,",
						"     ignoreNoFilesFound: false) ~> source1",
						"source1 sink(allowSchemaDrift: true,",
						"     validateSchema: false,",
						"     input(",
						"          prd_id as integer,",
						"          prd_key as string,",
						"          prd_nm as string,",
						"          prd_cost as decimal(18,0),",
						"          prd_line as string",
						"     ),",
						"     deletable:false,",
						"     insertable:true,",
						"     updateable:false,",
						"     upsertable:false,",
						"     truncate:true,",
						"     format: 'table',",
						"     skipDuplicateMapInputs: true,",
						"     skipDuplicateMapOutputs: true,",
						"     errorHandlingOption: 'stopOnFirstError',",
						"     mapColumn(",
						"          prd_id,",
						"          prd_key,",
						"          prd_nm,",
						"          prd_cost,",
						"          prd_line",
						"     )) ~> sink1"
					]
				}
			},
			"dependsOn": []
		},
		{
			"name": "[concat(parameters('factoryName'), '/bronze_df_productos_cat')]",
			"type": "Microsoft.DataFactory/factories/dataflows",
			"apiVersion": "2018-06-01",
			"properties": {
				"folder": {
					"name": "BRONZE"
				},
				"type": "MappingDataFlow",
				"typeProperties": {
					"sources": [
						{
							"dataset": {
								"referenceName": "productos_cat_csv",
								"type": "DatasetReference"
							},
							"name": "source1"
						}
					],
					"sinks": [
						{
							"dataset": {
								"referenceName": "bronze_sql_productos_cat",
								"type": "DatasetReference"
							},
							"name": "sink1"
						}
					],
					"transformations": [],
					"scriptLines": [
						"source(output(",
						"          ID as string,",
						"          CAT as string,",
						"          SUBCAT as string,",
						"          MAINTENANCE as string",
						"     ),",
						"     allowSchemaDrift: true,",
						"     validateSchema: false,",
						"     ignoreNoFilesFound: false) ~> source1",
						"source1 sink(allowSchemaDrift: true,",
						"     validateSchema: false,",
						"     input(",
						"          ID as string,",
						"          CAT as string,",
						"          SUBCAT as string,",
						"          MAINTENANCE as string",
						"     ),",
						"     deletable:false,",
						"     insertable:true,",
						"     updateable:false,",
						"     upsertable:false,",
						"     truncate:true,",
						"     format: 'table',",
						"     skipDuplicateMapInputs: true,",
						"     skipDuplicateMapOutputs: true,",
						"     errorHandlingOption: 'stopOnFirstError',",
						"     mapColumn(",
						"          ID,",
						"          CAT,",
						"          SUBCAT,",
						"          MAINTENANCE",
						"     )) ~> sink1"
					]
				}
			},
			"dependsOn": []
		},
		{
			"name": "[concat(parameters('factoryName'), '/BRONZE_PL_CLIENTES')]",
			"type": "Microsoft.DataFactory/factories/pipelines",
			"apiVersion": "2018-06-01",
			"properties": {
				"activities": [
					{
						"name": "Data flow1",
						"type": "ExecuteDataFlow",
						"dependsOn": [],
						"policy": {
							"timeout": "0.12:00:00",
							"retry": 0,
							"retryIntervalInSeconds": 30,
							"secureOutput": false,
							"secureInput": false
						},
						"userProperties": [],
						"typeProperties": {
							"dataflow": {
								"referenceName": "bronze_df_clientes",
								"type": "DataFlowReference",
								"parameters": {},
								"datasetParameters": {
									"source1": {},
									"sink1": {}
								}
							},
							"staging": {},
							"compute": {
								"coreCount": 8,
								"computeType": "General"
							},
							"traceLevel": "Fine",
							"continueOnError": true
						}
					}
				],
				"policy": {
					"elapsedTimeMetric": {}
				},
				"folder": {
					"name": "BRONZE"
				},
				"annotations": []
			},
			"dependsOn": []
		},
		{
			"name": "[concat(parameters('factoryName'), '/BRONZE_PL_CLIENTES_BD')]",
			"type": "Microsoft.DataFactory/factories/pipelines",
			"apiVersion": "2018-06-01",
			"properties": {
				"activities": [
					{
						"name": "Data flow1",
						"type": "ExecuteDataFlow",
						"dependsOn": [],
						"policy": {
							"timeout": "0.12:00:00",
							"retry": 0,
							"retryIntervalInSeconds": 30,
							"secureOutput": false,
							"secureInput": false
						},
						"userProperties": [],
						"typeProperties": {
							"dataflow": {
								"referenceName": "bronze_df_clientes_bd",
								"type": "DataFlowReference",
								"parameters": {},
								"datasetParameters": {
									"source1": {},
									"sink1": {}
								}
							},
							"staging": {},
							"compute": {
								"coreCount": 8,
								"computeType": "General"
							},
							"traceLevel": "Fine",
							"continueOnError": true
						}
					}
				],
				"policy": {
					"elapsedTimeMetric": {}
				},
				"folder": {
					"name": "BRONZE"
				},
				"annotations": []
			},
			"dependsOn": []
		},
		{
			"name": "[concat(parameters('factoryName'), '/BRONZE_PL_CLIENTES_LOC')]",
			"type": "Microsoft.DataFactory/factories/pipelines",
			"apiVersion": "2018-06-01",
			"properties": {
				"activities": [
					{
						"name": "Data flow1",
						"type": "ExecuteDataFlow",
						"dependsOn": [],
						"policy": {
							"timeout": "0.12:00:00",
							"retry": 0,
							"retryIntervalInSeconds": 30,
							"secureOutput": false,
							"secureInput": false
						},
						"userProperties": [],
						"typeProperties": {
							"dataflow": {
								"referenceName": "bronze_df_clientes_loc",
								"type": "DataFlowReference",
								"parameters": {},
								"datasetParameters": {
									"source1": {},
									"sink1": {}
								}
							},
							"staging": {},
							"compute": {
								"coreCount": 8,
								"computeType": "General"
							},
							"traceLevel": "Fine",
							"continueOnError": true
						}
					}
				],
				"policy": {
					"elapsedTimeMetric": {}
				},
				"folder": {
					"name": "BRONZE"
				},
				"annotations": []
			},
			"dependsOn": []
		},
		{
			"name": "[concat(parameters('factoryName'), '/BRONZE_PL_DETALLE_VENTAS')]",
			"type": "Microsoft.DataFactory/factories/pipelines",
			"apiVersion": "2018-06-01",
			"properties": {
				"activities": [
					{
						"name": "bronze_df_detalle_ventas",
						"type": "ExecuteDataFlow",
						"dependsOn": [],
						"policy": {
							"timeout": "0.12:00:00",
							"retry": 0,
							"retryIntervalInSeconds": 30,
							"secureOutput": false,
							"secureInput": false
						},
						"userProperties": [],
						"typeProperties": {
							"dataflow": {
								"referenceName": "bronze_df_detalle_ventas",
								"type": "DataFlowReference",
								"parameters": {},
								"datasetParameters": {
									"source1": {},
									"sink1": {}
								}
							},
							"staging": {},
							"compute": {
								"coreCount": 8,
								"computeType": "General"
							},
							"traceLevel": "Fine",
							"continueOnError": true
						}
					}
				],
				"policy": {
					"elapsedTimeMetric": {}
				},
				"folder": {
					"name": "BRONZE"
				},
				"annotations": []
			},
			"dependsOn": []
		},
		{
			"name": "[concat(parameters('factoryName'), '/BRONZE_PL_PRODUCTOS')]",
			"type": "Microsoft.DataFactory/factories/pipelines",
			"apiVersion": "2018-06-01",
			"properties": {
				"activities": [
					{
						"name": "bronze_df_productos",
						"type": "ExecuteDataFlow",
						"dependsOn": [],
						"policy": {
							"timeout": "0.12:00:00",
							"retry": 0,
							"retryIntervalInSeconds": 30,
							"secureOutput": false,
							"secureInput": false
						},
						"userProperties": [],
						"typeProperties": {
							"dataflow": {
								"referenceName": "bronze_df_productos",
								"type": "DataFlowReference",
								"parameters": {},
								"datasetParameters": {
									"source1": {},
									"sink1": {}
								}
							},
							"staging": {},
							"compute": {
								"coreCount": 8,
								"computeType": "General"
							},
							"traceLevel": "Fine",
							"continueOnError": true
						}
					}
				],
				"policy": {
					"elapsedTimeMetric": {}
				},
				"folder": {
					"name": "BRONZE"
				},
				"annotations": []
			},
			"dependsOn": [
				"[concat(variables('factoryId'), '/dataflows/bronze_df_productos')]"
			]
		},
		{
			"name": "[concat(parameters('factoryName'), '/BRONZE_PL_PRODUCTOS_CAT')]",
			"type": "Microsoft.DataFactory/factories/pipelines",
			"apiVersion": "2018-06-01",
			"properties": {
				"activities": [
					{
						"name": "bronze_df_productos_cat",
						"type": "ExecuteDataFlow",
						"dependsOn": [],
						"policy": {
							"timeout": "0.12:00:00",
							"retry": 0,
							"retryIntervalInSeconds": 30,
							"secureOutput": false,
							"secureInput": false
						},
						"userProperties": [],
						"typeProperties": {
							"dataflow": {
								"referenceName": "bronze_df_productos_cat",
								"type": "DataFlowReference",
								"parameters": {},
								"datasetParameters": {
									"source1": {},
									"sink1": {}
								}
							},
							"staging": {},
							"compute": {
								"coreCount": 8,
								"computeType": "General"
							},
							"traceLevel": "Fine",
							"continueOnError": true
						}
					}
				],
				"policy": {
					"elapsedTimeMetric": {}
				},
				"folder": {
					"name": "BRONZE"
				},
				"annotations": []
			},
			"dependsOn": [
				"[concat(variables('factoryId'), '/dataflows/bronze_df_productos_cat')]"
			]
		}
	]
}